importlinter/__init__.py
importlinter/api.py
importlinter/cli.py
importlinter/configuration.py
importlinter/py.typed
importlinter/pylint_output.py
importlinter/pylint_plugin.py
importlinter/adapters/__init__.py
importlinter/adapters/building.py
importlinter/adapters/filesystem.py
importlinter/adapters/printing.py
importlinter/adapters/timing.py
importlinter/adapters/user_options.py
importlinter/application/__init__.py
importlinter/application/app_config.py
importlinter/application/constants.py
importlinter/application/contract_utils.py
importlinter/application/file_finding.py
importlinter/application/formatters.py
importlinter/application/output.py
importlinter/application/rendering.py
importlinter/application/sentinels.py
importlinter/application/use_cases.py
importlinter/application/user_options.py
importlinter/application/ports/__init__.py
importlinter/application/ports/building.py
importlinter/application/ports/filesystem.py
importlinter/application/ports/printing.py
importlinter/application/ports/reporting.py
importlinter/application/ports/timing.py
importlinter/application/ports/user_options.py
importlinter/contracts/__init__.py
importlinter/contracts/_common.py
importlinter/contracts/forbidden.py
importlinter/contracts/independence.py
importlinter/contracts/layers.py
importlinter/domain/__init__.py
importlinter/domain/contract.py
importlinter/domain/fields.py
importlinter/domain/helpers.py
importlinter/domain/imports.py
pylint_import_linter-1.1.5.dist-info/licenses/AUTHORS.rst
pylint_import_linter-1.1.5.dist-info/licenses/LICENSE
pylint_import_linter-1.1.5.dist-info/METADATA
pylint_import_linter-1.1.5.dist-info/WHEEL
pylint_import_linter-1.1.5.dist-info/entry_points.txt
pylint_import_linter-1.1.5.dist-info/top_level.txt
pylint_import_linter-1.1.5.dist-info/RECORD
