Metadata-Version: 2.4
Name: pylint-import-linter
Version: 1.1.5
Summary: Enforces rules for the imports within and between Python packages.
Author-email: David Seddon <david@seddonym.me>, Siarhei Skuratovich <sOraCool@gmail.com>
License-Expression: BSD-2-Clause
Project-URL: Documentation, https://import-linter.readthedocs.io/
Project-URL: Source-code, https://github.com/seddonym/import-linter/
Classifier: Development Status :: 5 - Production/Stable
Classifier: Intended Audience :: Developers
Classifier: Operating System :: Unix
Classifier: Operating System :: POSIX
Classifier: Operating System :: Microsoft :: Windows
Classifier: Programming Language :: Python
Classifier: Programming Language :: Python :: 3.9
Classifier: Programming Language :: Python :: 3.10
Classifier: Programming Language :: Python :: 3.11
Classifier: Programming Language :: Python :: 3.12
Classifier: Programming Language :: Python :: 3.13
Classifier: Programming Language :: Python :: Implementation :: CPython
Classifier: Topic :: Utilities
Requires-Python: >=3.9
License-File: LICENSE
License-File: AUTHORS.rst
Requires-Dist: click<8.2.0,>=8.0.0; python_version < "3.10"
Requires-Dist: click>=8.2.1; python_version >= "3.10"
Requires-Dist: grimp>=3.9
Requires-Dist: tomli>=2.2.1; python_version < "3.11"
Requires-Dist: typing-extensions>=4.14.1
Requires-Dist: pylint>=3.0.0
Requires-Dist: types-pyyaml>=6.0.12.20250516
Dynamic: license-file
